spScriptTest3Py/ScriptTest3.py
spScriptTest3Py/__init__.py
spscripttest3py-1.0.1.dist-info/METADATA
spscripttest3py-1.0.1.dist-info/WHEEL
spscripttest3py-1.0.1.dist-info/licenses/LICENSE
spscripttest3py-1.0.1.dist-info/RECORD
