Metadata-Version: 2.4
Name: spScriptTest3Py
Version: 1.0.1
Summary: A Python package for ...
Project-URL: Homepage, https://github.com/krokoreit/spScriptTest3Py
Project-URL: Source Code, https://github.com/krokoreit/spScriptTest3Py
Author-email: krokoreit <krokoreit@gmail.com>
License-Expression: MIT
License-File: LICENSE
Keywords: key1
Classifier: Operating System :: OS Independent
Classifier: Programming Language :: Python :: 3
Requires-Python: >=3.10
